tcviewer/__init__.py
tcviewer/materials.py
tcviewer/mol_widget.py
tcviewer/screen.py
tcviewer/settings.py
TCviewer-0.1.12.dist-info/LICENSE
TCviewer-0.1.12.dist-info/METADATA
TCviewer-0.1.12.dist-info/WHEEL
TCviewer-0.1.12.dist-info/top_level.txt
TCviewer-0.1.12.dist-info/RECORD
