Metadata-Version: 2.1
Name: TCviewer
Version: 0.1.12
Summary: Molecular and Surface drawing program.
Author-email: Yuman Hordijk <yumanhordijk@gmail.com>
Classifier: Programming Language :: Python :: 3
Classifier: License :: OSI Approved :: MIT License
Classifier: Operating System :: OS Independent
Requires-Python: >=3.7
License-File: LICENSE
Requires-Dist: GitPython
Requires-Dist: numpy
Requires-Dist: vtk>=9.5.2
Requires-Dist: plams
Requires-Dist: TCutility
Requires-Dist: PySide6-essentials
